{
  "id": "clinical__book__ef119c125c92",
  "kg_id": "clinical",
  "kg_title": "Clinical KG",
  "title": "Cognitive Therapy of Depression",
  "kind": "book",
  "book": "Cognitive Therapy of Depression",
  "book_group": "clinical",
  "schema_name": "Clinical Mental Health KG",
  "module": "clinical_core",
  "schema_version": "",
  "fusion_method": "",
  "source_books": [],
  "node_types": [
    {
      "type": "Person",
      "description": "An individual involved in therapy, including patients, therapists, and authors.",
      "properties": [
        {
          "name": "full_name",
          "description": "The person's full name"
        },
        {
          "name": "role",
          "description": "Role in therapy or authorship (e.g., patient, therapist, author)"
        },
        {
          "name": "credentials",
          "description": "Professional qualifications or degrees"
        },
        {
          "name": "biographical_summary",
          "description": "Brief biography or relevant background"
        },
        {
          "name": "cultural_background",
          "description": "Cultural or religious background, if relevant"
        }
      ],
      "supported_by_books": [],
      "supported_by_chapters": [
        "About the Authors",
        "2. The Role of Emotion and the Nature of the Therapeutic Relationship",
        "14. Extended Case Example",
        "12. Modifications for Different Settings and Populations"
      ]
    },
    {
      "type": "Diagnosis",
      "description": "A clinical diagnosis or mental health condition assigned to a patient.",
      "properties": [
        {
          "name": "diagnosis_name",
          "description": "Name of the diagnosis (e.g., Major Depressive Disorder)"
        },
        {
          "name": "diagnostic_criteria",
          "description": "Criteria or description of the diagnosis"
        },
        {
          "name": "onset_age",
          "description": "Age at onset"
        },
        {
          "name": "severity",
          "description": "Severity of the condition"
        },
        {
          "name": "comorbid_conditions",
          "description": "List of comorbid diagnoses"
        }
      ],
      "supported_by_books": [],
      "supported_by_chapters": [
        "1. Overview",
        "8. Addressing Comorbid Disorders",
        "14. Extended Case Example",
        "15. Cognitive Therapy and Antidepressant Medications"
      ]
    },
    {
      "type": "Symptom",
      "description": "A psychological, emotional, behavioral, or physiological symptom experienced by a patient.",
      "properties": [
        {
          "name": "symptom_name",
          "description": "Name of the symptom"
        },
        {
          "name": "symptom_type",
          "description": "Type (e.g., emotional, behavioral, physiological)"
        },
        {
          "name": "severity",
          "description": "Severity rating"
        },
        {
          "name": "duration",
          "description": "Duration of the symptom"
        },
        {
          "name": "onset",
          "description": "Onset timing"
        }
      ],
      "supported_by_books": [],
      "supported_by_chapters": [
        "1. Overview",
        "4. The Initial Session: Providing a Cognitive Rationale",
        "5. Application of Behavioral Techniques",
        "9. Treating the Suicidal Patient",
        "14. Extended Case Example"
      ]
    },
    {
      "type": "CognitiveConcept",
      "description": "A cognitive construct relevant to therapy, such as automatic thoughts, core beliefs, schemas, or cognitive distortions.",
      "properties": [
        {
          "name": "concept_type",
          "description": "Type of cognitive concept (e.g., automatic thought, core belief, schema, cognitive distortion)"
        },
        {
          "name": "description",
          "description": "Description or definition of the concept"
        },
        {
          "name": "example",
          "description": "Example instance of the concept"
        }
      ],
      "supported_by_books": [],
      "supported_by_chapters": [
        "1. Overview",
        "6. Integrating Cognitive Techniques",
        "7. Schemas: Core Beliefs and Underlying Assumptions",
        "13. Common Problems Encountered in Cognitive Therapy",
        "14. Extended Case Example"
      ]
    },
    {
      "type": "TherapeuticTechnique",
      "description": "A specific intervention, method, or tool used in therapy.",
      "properties": [
        {
          "name": "technique_name",
          "description": "Name of the technique (e.g., Socratic questioning, Thought Record)"
        },
        {
          "name": "description",
          "description": "Description of the technique"
        },
        {
          "name": "purpose",
          "description": "Therapeutic purpose or goal"
        },
        {
          "name": "applicability",
          "description": "Applicable diagnoses, symptoms, or populations"
        }
      ],
      "supported_by_books": [],
      "supported_by_chapters": [
        "3. Structure of the Therapeutic Interview",
        "5. Application of Behavioral Techniques",
        "6. Integrating Cognitive Techniques",
        "7. Schemas: Core Beliefs and Underlying Assumptions",
        "10. Integration of Homework into Therapy",
        "14. Extended Case Example"
      ]
    },
    {
      "type": "TherapeuticSession",
      "description": "A single session or encounter in the course of therapy.",
      "properties": [
        {
          "name": "session_number",
          "description": "Ordinal number of the session"
        },
        {
          "name": "date",
          "description": "Date of the session"
        },
        {
          "name": "session_type",
          "description": "Type (e.g., initial, regular, termination, booster)"
        },
        {
          "name": "agenda",
          "description": "Planned topics or goals for the session"
        },
        {
          "name": "summary",
          "description": "Summary of session content"
        },
        {
          "name": "homework_assigned",
          "description": "Homework or tasks assigned"
        },
        {
          "name": "mood_rating",
          "description": "Patient's mood rating during session"
        }
      ],
      "supported_by_books": [],
      "supported_by_chapters": [
        "3. Structure of the Therapeutic Interview",
        "4. The Initial Session: Providing a Cognitive Rationale",
        "10. Integration of Homework into Therapy",
        "11. Termination and Relapse Prevention",
        "14. Extended Case Example"
      ]
    },
    {
      "type": "TreatmentPlan",
      "description": "A structured plan outlining therapeutic goals, interventions, and strategies for a patient.",
      "properties": [
        {
          "name": "goals",
          "description": "List of treatment goals"
        },
        {
          "name": "interventions",
          "description": "Planned interventions or techniques"
        },
        {
          "name": "target_symptoms",
          "description": "Symptoms targeted by the plan"
        },
        {
          "name": "relapse_prevention_strategies",
          "description": "Strategies for preventing relapse"
        },
        {
          "name": "cultural_considerations",
          "description": "Cultural or religious factors considered in planning"
        }
      ],
      "supported_by_books": [],
      "supported_by_chapters": [
        "4. The Initial Session: Providing a Cognitive Rationale",
        "11. Termination and Relapse Prevention",
        "12. Modifications for Different Settings and Populations",
        "14. Extended Case Example"
      ]
    },
    {
      "type": "Measure",
      "description": "A standardized assessment tool or scale used to evaluate symptoms, risk, or progress.",
      "properties": [
        {
          "name": "measure_name",
          "description": "Name of the measure (e.g., BDI, PHQ-9, Hopelessness Scale)"
        },
        {
          "name": "description",
          "description": "Description of the measure"
        },
        {
          "name": "target_construct",
          "description": "What the measure assesses"
        },
        {
          "name": "scoring_method",
          "description": "How the measure is scored"
        },
        {
          "name": "administration_frequency",
          "description": "How often the measure is administered"
        }
      ],
      "supported_by_books": [],
      "supported_by_chapters": [
        "4. The Initial Session: Providing a Cognitive Rationale",
        "9. Treating the Suicidal Patient",
        "14. Extended Case Example",
        "15. Cognitive Therapy and Antidepressant Medications",
        "Index"
      ]
    },
    {
      "type": "Medication",
      "description": "A pharmacological treatment used in the management of depression or comorbid conditions.",
      "properties": [
        {
          "name": "medication_name",
          "description": "Name of the medication"
        },
        {
          "name": "medication_class",
          "description": "Class of medication (e.g., SSRI, TCA)"
        },
        {
          "name": "indications",
          "description": "Indications for use"
        },
        {
          "name": "side_effects",
          "description": "Common side effects"
        },
        {
          "name": "dosage",
          "description": "Typical dosage information"
        }
      ],
      "supported_by_books": [],
      "supported_by_chapters": [
        "15. Cognitive Therapy and Antidepressant Medications",
        "16. Cognitive Therapy: Efficacious and Enduring"
      ]
    },
    {
      "type": "Setting",
      "description": "A context or environment in which therapy is delivered (e.g., outpatient, inpatient, group, primary care).",
      "properties": [
        {
          "name": "setting_type",
          "description": "Type of setting (e.g., outpatient, inpatient, group, primary care)"
        },
        {
          "name": "description",
          "description": "Description of the setting"
        },
        {
          "name": "modifications",
          "description": "Modifications to therapy required for this setting"
        }
      ],
      "supported_by_books": [],
      "supported_by_chapters": [
        "12. Modifications for Different Settings and Populations"
      ]
    },
    {
      "type": "Population",
      "description": "A specific patient group or demographic relevant to therapy (e.g., children, adolescents, older adults, cultural groups).",
      "properties": [
        {
          "name": "population_type",
          "description": "Type of population (e.g., children, adolescents, older adults, specific cultural group)"
        },
        {
          "name": "description",
          "description": "Description of the population"
        },
        {
          "name": "special_considerations",
          "description": "Special considerations for therapy with this population"
        }
      ],
      "supported_by_books": [],
      "supported_by_chapters": [
        "12. Modifications for Different Settings and Populations",
        "16. Cognitive Therapy: Efficacious and Enduring"
      ]
    }
  ],
  "edge_types": [
    {
      "source_type": "Person",
      "relation": "HAS_DIAGNOSIS",
      "target_type": "Diagnosis",
      "description": "Indicates that a person (patient) has been assigned a specific diagnosis.",
      "properties": [],
      "supported_by_books": [],
      "supported_by_chapters": [
        "1. Overview",
        "8. Addressing Comorbid Disorders",
        "14. Extended Case Example"
      ]
    },
    {
      "source_type": "Diagnosis",
      "relation": "HAS_SYMPTOM",
      "target_type": "Symptom",
      "description": "Links a diagnosis to its associated symptoms.",
      "properties": [],
      "supported_by_books": [],
      "supported_by_chapters": [
        "1. Overview",
        "4. The Initial Session: Providing a Cognitive Rationale",
        "8. Addressing Comorbid Disorders"
      ]
    },
    {
      "source_type": "Person",
      "relation": "EXPERIENCES_SYMPTOM",
      "target_type": "Symptom",
      "description": "Indicates that a person is currently experiencing a symptom.",
      "properties": [
        {
          "name": "severity_rating",
          "description": "Severity of the symptom for this person"
        },
        {
          "name": "onset_date",
          "description": "Date when the symptom began"
        }
      ],
      "supported_by_books": [],
      "supported_by_chapters": [
        "4. The Initial Session: Providing a Cognitive Rationale",
        "14. Extended Case Example"
      ]
    },
    {
      "source_type": "Person",
      "relation": "HAS_COGNITIVE_CONCEPT",
      "target_type": "CognitiveConcept",
      "description": "Indicates that a person holds or exhibits a particular cognitive concept (e.g., core belief, automatic thought).",
      "properties": [
        {
          "name": "evidence",
          "description": "Evidence or examples from therapy"
        }
      ],
      "supported_by_books": [],
      "supported_by_chapters": [
        "6. Integrating Cognitive Techniques",
        "7. Schemas: Core Beliefs and Underlying Assumptions",
        "14. Extended Case Example"
      ]
    },
    {
      "source_type": "Person",
      "relation": "PARTICIPATES_IN_SESSION",
      "target_type": "TherapeuticSession",
      "description": "Indicates that a person (patient or therapist) participated in a specific therapeutic session.",
      "properties": [
        {
          "name": "role",
          "description": "Role in the session (e.g., patient, therapist, family member)"
        }
      ],
      "supported_by_books": [],
      "supported_by_chapters": [
        "3. Structure of the Therapeutic Interview",
        "14. Extended Case Example"
      ]
    },
    {
      "source_type": "TherapeuticSession",
      "relation": "USES_TECHNIQUE",
      "target_type": "TherapeuticTechnique",
      "description": "Indicates that a specific therapeutic technique was used during a session.",
      "properties": [
        {
          "name": "purpose",
          "description": "Purpose of using the technique in this session"
        }
      ],
      "supported_by_books": [],
      "supported_by_chapters": [
        "3. Structure of the Therapeutic Interview",
        "5. Application of Behavioral Techniques",
        "6. Integrating Cognitive Techniques",
        "14. Extended Case Example"
      ]
    },
    {
      "source_type": "TherapeuticSession",
      "relation": "ASSIGNS_HOMEWORK",
      "target_type": "TherapeuticTechnique",
      "description": "Indicates that a technique was assigned as homework in a session.",
      "properties": [
        {
          "name": "homework_instructions",
          "description": "Instructions or details of the homework assignment"
        }
      ],
      "supported_by_books": [],
      "supported_by_chapters": [
        "10. Integration of Homework into Therapy",
        "14. Extended Case Example"
      ]
    },
    {
      "source_type": "Person",
      "relation": "FOLLOWS_TREATMENT_PLAN",
      "target_type": "TreatmentPlan",
      "description": "Indicates that a person is following a specific treatment plan.",
      "properties": [
        {
          "name": "start_date",
          "description": "Date treatment plan began"
        },
        {
          "name": "adherence_level",
          "description": "Level of adherence to the plan"
        }
      ],
      "supported_by_books": [],
      "supported_by_chapters": [
        "4. The Initial Session: Providing a Cognitive Rationale",
        "11. Termination and Relapse Prevention",
        "14. Extended Case Example"
      ]
    },
    {
      "source_type": "TreatmentPlan",
      "relation": "TARGETS_SYMPTOM",
      "target_type": "Symptom",
      "description": "Indicates that a treatment plan is designed to address a specific symptom.",
      "properties": [],
      "supported_by_books": [],
      "supported_by_chapters": [
        "4. The Initial Session: Providing a Cognitive Rationale",
        "11. Termination and Relapse Prevention"
      ]
    },
    {
      "source_type": "TreatmentPlan",
      "relation": "INCLUDES_TECHNIQUE",
      "target_type": "TherapeuticTechnique",
      "description": "Indicates that a treatment plan includes a specific therapeutic technique.",
      "properties": [],
      "supported_by_books": [],
      "supported_by_chapters": [
        "5. Application of Behavioral Techniques",
        "6. Integrating Cognitive Techniques",
        "7. Schemas: Core Beliefs and Underlying Assumptions"
      ]
    },
    {
      "source_type": "Person",
      "relation": "ASSESSED_BY_MEASURE",
      "target_type": "Measure",
      "description": "Indicates that a person has been assessed using a specific measure or scale.",
      "properties": [
        {
          "name": "score",
          "description": "Score obtained on the measure"
        },
        {
          "name": "assessment_date",
          "description": "Date of assessment"
        }
      ],
      "supported_by_books": [],
      "supported_by_chapters": [
        "4. The Initial Session: Providing a Cognitive Rationale",
        "9. Treating the Suicidal Patient",
        "14. Extended Case Example"
      ]
    },
    {
      "source_type": "Diagnosis",
      "relation": "TREATED_WITH_MEDICATION",
      "target_type": "Medication",
      "description": "Indicates that a diagnosis is treated with a specific medication.",
      "properties": [
        {
          "name": "treatment_phase",
          "description": "Phase of treatment (e.g., acute, maintenance, relapse prevention)"
        }
      ],
      "supported_by_books": [],
      "supported_by_chapters": [
        "15. Cognitive Therapy and Antidepressant Medications",
        "16. Cognitive Therapy: Efficacious and Enduring"
      ]
    },
    {
      "source_type": "Person",
      "relation": "PRESCRIBED_MEDICATION",
      "target_type": "Medication",
      "description": "Indicates that a person has been prescribed a specific medication.",
      "properties": [
        {
          "name": "dosage",
          "description": "Dosage prescribed"
        },
        {
          "name": "start_date",
          "description": "Date medication was started"
        },
        {
          "name": "adherence",
          "description": "Adherence to medication regimen"
        }
      ],
      "supported_by_books": [],
      "supported_by_chapters": [
        "15. Cognitive Therapy and Antidepressant Medications"
      ]
    },
    {
      "source_type": "TherapeuticSession",
      "relation": "CONDUCTED_IN_SETTING",
      "target_type": "Setting",
      "description": "Indicates the setting in which a therapeutic session took place.",
      "properties": [],
      "supported_by_books": [],
      "supported_by_chapters": [
        "12. Modifications for Different Settings and Populations"
      ]
    },
    {
      "source_type": "Person",
      "relation": "BELONGS_TO_POPULATION",
      "target_type": "Population",
      "description": "Indicates that a person is part of a specific population or demographic group.",
      "properties": [],
      "supported_by_books": [],
      "supported_by_chapters": [
        "12. Modifications for Different Settings and Populations",
        "16. Cognitive Therapy: Efficacious and Enduring"
      ]
    },
    {
      "source_type": "TreatmentPlan",
      "relation": "CONSIDERS_CULTURAL_FACTORS",
      "target_type": "Population",
      "description": "Indicates that a treatment plan takes into account cultural or population-specific considerations.",
      "properties": [
        {
          "name": "cultural_alignment_notes",
          "description": "Notes on how the plan is adapted for cultural or religious alignment"
        }
      ],
      "supported_by_books": [],
      "supported_by_chapters": [
        "12. Modifications for Different Settings and Populations"
      ]
    }
  ],
  "stats": {
    "nodes": 11,
    "edges": 16,
    "source_books": 0
  }
}
